{".class": "MypyFile", "_fullname": "graphscale_todo.pent", "_name": null, "is_stub": false, "names": {".class": "SymbolTable", "CreateTodoItemData": {".class": "SymbolTableNode", "cross_ref": "graphscale_todo.pent.mutations.CreateTodoItemData", "kind": "Gdef"}, "CreateTodoItemPayload": {".class": "SymbolTableNode", "cross_ref": "graphscale_todo.pent.mutations.CreateTodoItemPayload", "kind": "Gdef"}, "CreateTodoListData": {".class": "SymbolTableNode", "cross_ref": "graphscale_todo.pent.mutations.CreateTodoListData", "kind": "Gdef"}, "CreateTodoListPayload": {".class": "SymbolTableNode", "cross_ref": "graphscale_todo.pent.mutations.CreateTodoListPayload", "kind": "Gdef"}, "CreateTodoUserData": {".class": "SymbolTableNode", "cross_ref": "graphscale_todo.pent.mutations.CreateTodoUserData", "kind": "Gdef"}, "CreateTodoUserPayload": {".class": "SymbolTableNode", "cross_ref": "graphscale_todo.pent.mutations.CreateTodoUserPayload", "kind": "Gdef"}, "DeleteTodoItemPayload": {".class": "SymbolTableNode", "cross_ref": "graphscale_todo.pent.mutations.DeleteTodoItemPayload", "kind": "Gdef"}, "DeleteTodoUserPayload": {".class": "SymbolTableNode", "cross_ref": "graphscale_todo.pent.mutations.DeleteTodoUserPayload", "kind": "Gdef"}, "PentMutationData": {".class": "SymbolTableNode", "cross_ref": "graphscale_todo.pent.mutations.PentMutationData", "kind": "Gdef"}, "PentMutationPayload": {".class": "SymbolTableNode", "cross_ref": "graphscale_todo.pent.mutations.PentMutationPayload", "kind": "Gdef"}, "Root": {".class": "SymbolTableNode", "cross_ref": "graphscale_todo.pent.pents.Root", "kind": "Gdef"}, "TodoItem": {".class": "SymbolTableNode", "cross_ref": "graphscale_todo.pent.pents.TodoItem", "kind": "Gdef"}, "TodoList": {".class": "SymbolTableNode", "cross_ref": "graphscale_todo.pent.pents.TodoList", "kind": "Gdef"}, "TodoUser": {".class": "SymbolTableNode", "cross_ref": "graphscale_todo.pent.pents.TodoUser", "kind": "Gdef"}, "UpdateTodoUserData": {".class": "SymbolTableNode", "cross_ref": "graphscale_todo.pent.mutations.UpdateTodoUserData", "kind": "Gdef"}, "UpdateTodoUserPayload": {".class": "SymbolTableNode", "cross_ref": "graphscale_todo.pent.mutations.UpdateTodoUserPayload", "kind": "Gdef"}, "__doc__": {".class": "SymbolTableNode", "kind": "Gdef", "node": {".class": "Var", "flags": ["is_ready"], "fullname": "graphscale_todo.pent.__doc__", "name": "__doc__", "type": "builtins.str"}}, "__file__": {".class": "SymbolTableNode", "kind": "Gdef", "node": {".class": "Var", "flags": ["is_ready"], "fullname": "graphscale_todo.pent.__file__", "name": "__file__", "type": "builtins.str"}}, "__name__": {".class": "SymbolTableNode", "kind": "Gdef", "node": {".class": "Var", "flags": ["is_ready"], "fullname": "graphscale_todo.pent.__name__", "name": "__name__", "type": "builtins.str"}}, "__package__": {".class": "SymbolTableNode", "kind": "Gdef", "node": {".class": "Var", "flags": ["is_ready"], "fullname": "graphscale_todo.pent.__package__", "name": "__package__", "type": "builtins.str"}}, "check": {".class": "SymbolTableNode", "cross_ref": "graphscale_todo.pent.mutations.check", "kind": "Gdef"}, "create_pent": {".class": "SymbolTableNode", "cross_ref": "graphscale_todo.pent.mutations.create_pent", "kind": "Gdef"}, "generated": {".class": "SymbolTableNode", "cross_ref": "graphscale_todo.pent.generated", "kind": "ModuleRef"}, "mutations": {".class": "SymbolTableNode", "cross_ref": "graphscale_todo.pent.mutations", "kind": "ModuleRef"}, "namedtuple": {".class": "SymbolTableNode", "cross_ref": "collections.namedtuple", "kind": "Gdef"}, "pents": {".class": "SymbolTableNode", "cross_ref": "graphscale_todo.pent.pents", "kind": "ModuleRef"}}, "path": "/Users/schrockn/code/schrockn_github/graphscale_todo/graphscale_todo/pent/__init__.py"}
